{
	"loader": "forge:separate_transforms",
	"gui_light": "front",
	"base": {
		"parent": "mmm:custom/orange_candle_lit",
		"textures": {
			"0": "mmm:item/models/orange_candle_lit"
		}
	},
	"perspectives": {
		"gui": {
			"parent": "item/generated",
			"textures": {
				"layer0": "mmm:item/orange_candle_lit"
			},
			"gui_light": "front"
		},
		"ground": {
			"parent": "item/generated",
			"textures": {
				"layer0": "mmm:item/orange_candle_lit"
			}
		},
		"fixed": {
			"parent": "item/generated",
			"textures": {
				"layer0": "mmm:item/orange_candle_lit"
			}
		}
	}
}
